AUTHORS.rst
CONTRIBUTING.rst
HISTORY.rst
LICENSE
MANIFEST.in
README.md
pyproject.toml
requirements-dev.txt
requirements.in
requirements.txt
setup.cfg
setup.py
clpso.egg-info/PKG-INFO
clpso.egg-info/SOURCES.txt
clpso.egg-info/dependency_links.txt
clpso.egg-info/not-zip-safe
clpso.egg-info/requires.txt
clpso.egg-info/top_level.txt
docs/Makefile
docs/authors.rst
docs/conf.py
docs/contributing.rst
docs/dev.api.rst
docs/dev.loop.rst
docs/dev.optimizer.rst
docs/features.rst
docs/history.rst
docs/index.rst
docs/installation.rst
docs/intro.rst
docs/make.bat
docs/pyswarms-header.png
docs/tutorials.rst
docs/usecases.rst
docs/api/_pyswarms.backend.rst
docs/api/_pyswarms.base.classes.rst
docs/api/_pyswarms.optimizers.rst
docs/api/_pyswarms.utils.rst
docs/api/pyswarms.backend.rst
docs/api/pyswarms.base.rst
docs/api/pyswarms.discrete.rst
docs/api/pyswarms.handlers.rst
docs/api/pyswarms.single.rst
docs/api/pyswarms.swarms.rst
docs/api/pyswarms.topology.rst
docs/api/pyswarms.utils.decorators.rst
docs/api/pyswarms.utils.functions.rst
docs/api/pyswarms.utils.plotters.rst
docs/api/pyswarms.utils.reporter.rst
docs/api/pyswarms.utils.search.rst
docs/assets/inheritance.png
docs/assets/optimization_loop.png
docs/assets/pyswarms_api.png
docs/examples/tutorials/optimization_loop.png
docs/examples/tutorials/plot0.gif
docs/examples/tutorials/plot1.gif
pyswarms/__init__.py
pyswarms/backend/__init__.py
pyswarms/backend/generators.py
pyswarms/backend/handlers.py
pyswarms/backend/operators.py
pyswarms/backend/swarms.py
pyswarms/backend/topology/__init__.py
pyswarms/backend/topology/base.py
pyswarms/backend/topology/pyramid.py
pyswarms/backend/topology/random.py
pyswarms/backend/topology/ring.py
pyswarms/backend/topology/star.py
pyswarms/backend/topology/von_neumann.py
pyswarms/base/__init__.py
pyswarms/base/base_discrete.py
pyswarms/base/base_single.py
pyswarms/discrete/__init__.py
pyswarms/discrete/binary.py
pyswarms/single/__init__.py
pyswarms/single/clpso_lot.py
pyswarms/single/general_optimizer.py
pyswarms/single/global_best.py
pyswarms/single/local_best.py
pyswarms/utils/__init__.py
pyswarms/utils/decorators/__init__.py
pyswarms/utils/decorators/decorators.py
