Metadata-Version: 2.1
Name: clpso
Version: 0.0.1
Summary: clpso
Home-page: https://github.com/ljvmiranda921/pyswarms
Author: Lester James V. Miranda
Author-email: ljvmiranda@gmail.com
License: MIT license
Keywords: pyswarms
Platform: UNKNOWN
Classifier: Development Status :: 3 - Alpha
Classifier: Intended Audience :: Developers
Classifier: Intended Audience :: Education
Classifier: Intended Audience :: Science/Research
Classifier: License :: OSI Approved :: MIT License
Classifier: Natural Language :: English
Classifier: Topic :: Scientific/Engineering
Classifier: Programming Language :: Python :: 3.4
Classifier: Programming Language :: Python :: 3.5
Classifier: Programming Language :: Python :: 3.6
Provides-Extra: test
